sauce_api_mcp/__init__.py
sauce_api_mcp/__main__.py
sauce_api_mcp/main.py
sauce_api_mcp/models.py
sauce_api_mcp/rdc_openapi.py
sauce_api_mcp/api/__init__.py
sauce_api_mcp/shared/__init__.py
sauce_api_mcp-1.1.0.dist-info/licenses/LICENSE
sauce_api_mcp-1.1.0.dist-info/METADATA
sauce_api_mcp-1.1.0.dist-info/WHEEL
sauce_api_mcp-1.1.0.dist-info/entry_points.txt
sauce_api_mcp-1.1.0.dist-info/top_level.txt
sauce_api_mcp-1.1.0.dist-info/RECORD
