Metadata-Version: 2.4
Name: sauce-api-mcp
Version: 1.1.0
Summary: MCP servers for Sauce Labs APIs (Core & RDC OpenAPI)
Author-email: Marcus Merrell <mmerrell@gmail.com>
License: Apache-2.0
Classifier: Development Status :: 5 - Production/Stable
Classifier: Intended Audience :: Developers
Classifier: License :: OSI Approved :: Apache Software License
Classifier: Programming Language :: Python :: 3
Classifier: Programming Language :: Python :: 3.9
Classifier: Programming Language :: Python :: 3.10
Classifier: Programming Language :: Python :: 3.11
Classifier: Programming Language :: Python :: 3.12
Requires-Python: >=3.10
License-File: LICENSE
Requires-Dist: httpx>=0.24.0
Requires-Dist: pydantic>=2.0
Requires-Dist: mcp>=1.10.1
Requires-Dist: pyyaml>=6.0
Requires-Dist: fastmcp>=2.10.6
Provides-Extra: test
Requires-Dist: pytest; extra == "test"
Requires-Dist: pytest-asyncio; extra == "test"
Dynamic: license-file
